numpy_display.py
setup.py
numpy_display.egg-info/PKG-INFO
numpy_display.egg-info/SOURCES.txt
numpy_display.egg-info/dependency_links.txt
numpy_display.egg-info/requires.txt
numpy_display.egg-info/top_level.txt